mapwidget/__init__.py
mapwidget/basemaps.py
mapwidget/cesium.py
mapwidget/leaflet.py
mapwidget/mapbox.py
mapwidget/maplibre.py
mapwidget/openlayers.py
mapwidget/javascript/cesium.js
mapwidget/javascript/leaflet.js
mapwidget/javascript/mapbox.js
mapwidget/javascript/maplibre.js
mapwidget/javascript/openlayers.js
mapwidget/styles/cesium.css
mapwidget/styles/leaflet.css
mapwidget/styles/mapbox.css
mapwidget/styles/maplibre.css
mapwidget/styles/openlayers.css
mapwidget-0.2.0.dist-info/licenses/LICENSE
mapwidget-0.2.0.dist-info/METADATA
mapwidget-0.2.0.dist-info/WHEEL
mapwidget-0.2.0.dist-info/top_level.txt
mapwidget-0.2.0.dist-info/RECORD
