Metadata-Version: 2.4
Name: mapwidget
Version: 0.2.0
Summary: Custom Jupyter widgets for creating interactive maps
Author-email: Qiusheng Wu <giswqs@gmail.com>
License: MIT license
Project-URL: Homepage, https://github.com/opengeos/mapwidget
Keywords: mapwidget
Classifier: Development Status :: 2 - Pre-Alpha
Classifier: Intended Audience :: Developers
Classifier: License :: OSI Approved :: MIT License
Classifier: Natural Language :: English
Classifier: Programming Language :: Python :: 3
Classifier: Programming Language :: Python :: 3.9
Classifier: Programming Language :: Python :: 3.10
Classifier: Programming Language :: Python :: 3.11
Classifier: Programming Language :: Python :: 3.12
Classifier: Programming Language :: Python :: 3.13
License-File: LICENSE
Requires-Dist: anywidget>=0.9.0
Requires-Dist: xyzservices>=2025.4.0
Dynamic: license-file
